{
    "0875344368": {
        "callin": {
            "0875344368": 8
        },
        "callout": {
            "0875344368": 7
        }
    },
    "0612182785": {
        "callin": {
            "0612182785": 4
        },
        "callout": {
            "0612182785": 11
        }
    },
    "0688749360": {
        "callin": {
            "0688749360": 9
        },
        "callout": {
            "0688749360": 1
        }
    },
    "0848643276": {
        "callin": {
            "0848643276": 5
        },
        "callout": {
            "0848643276": 7
        }
    },
    "0363661308": {
        "callin": {
            "0363661308": 10
        },
        "callout": {
            "0363661308": 9
        }
    },
    "0887597506": {
        "callin": {
            "0887597506": 4
        },
        "callout": {
            "0887597506": 8
        }
    },
    "0920187348": {
        "callin": {
            "0920187348": 6
        },
        "callout": {
            "0920187348": 9
        }
    },
    "0603321665": {
        "callin": {
            "0603321665": 11
        },
        "callout": {
            "0603321665": 11
        }
    },
    "0597511688": {
        "callin": {
            "0597511688": 9
        },
        "callout": {
            "0597511688": 6
        }
    },
    "0563350785": {
        "callin": {
            "0563350785": 4
        },
        "callout": {
            "0563350785": 8
        }
    }
}